[
  {
    "id": "syn-1",
    "ua": "Mozilla/5.0 (iPhone; CPU iPhone OS 15_0 like Mac OS X) AppleWebKit/605.1.15 (KHTML, like Gecko) Version/26.0 Mobile/15E148 Safari/604.1",
    "locale": "de-DE",
    "nextVisitAt": 1761286983457,
    "affinity": [
      "sci-fi",
      "drama"
    ]
  },
  {
    "id": "syn-2",
    "ua": "Mozilla/5.0 (Windows NT 10.0; Win64; x64) AppleWebKit/537.36 (KHTML, like Gecko) Chrome/141.0.7390.37 Safari/537.36",
    "locale": "sl-SI",
    "nextVisitAt": 1761167139038,
    "affinity": [
      "kids",
      "family"
    ]
  },
  {
    "id": "syn-3",
    "ua": "Mozilla/5.0 (Windows NT 10.0; Win64; x64) AppleWebKit/537.36 (KHTML, like Gecko) Chrome/141.0.7390.37 Safari/537.36",
    "locale": "de-DE",
    "nextVisitAt": 1760994784098,
    "affinity": [
      "sci-fi",
      "drama"
    ]
  },
  {
    "id": "syn-4",
    "ua": "Mozilla/5.0 (iPhone; CPU iPhone OS 15_0 like Mac OS X) AppleWebKit/605.1.15 (KHTML, like Gecko) Version/26.0 Mobile/15E148 Safari/604.1",
    "locale": "sl-SI",
    "nextVisitAt": 1761014106711,
    "affinity": [
      "kids",
      "family"
    ]
  },
  {
    "id": "syn-5",
    "ua": "Mozilla/5.0 (Windows NT 10.0; Win64; x64) AppleWebKit/537.36 (KHTML, like Gecko) Chrome/141.0.7390.37 Safari/537.36",
    "locale": "de-DE",
    "nextVisitAt": 1761042621640,
    "affinity": [
      "sci-fi",
      "drama"
    ]
  },
  {
    "id": "syn-6",
    "ua": "Mozilla/5.0 (Windows NT 10.0; Win64; x64) AppleWebKit/537.36 (KHTML, like Gecko) Chrome/141.0.7390.37 Safari/537.36",
    "locale": "sl-SI",
    "nextVisitAt": 1761080030401,
    "affinity": [
      "kids",
      "family"
    ]
  },
  {
    "id": "syn-7",
    "ua": "Mozilla/5.0 (iPhone; CPU iPhone OS 15_0 like Mac OS X) AppleWebKit/605.1.15 (KHTML, like Gecko) Version/26.0 Mobile/15E148 Safari/604.1",
    "locale": "de-DE",
    "nextVisitAt": 1761421019124,
    "affinity": [
      "sci-fi",
      "drama"
    ]
  },
  {
    "id": "syn-8",
    "ua": "Mozilla/5.0 (Windows NT 10.0; Win64; x64) AppleWebKit/537.36 (KHTML, like Gecko) Chrome/141.0.7390.37 Safari/537.36",
    "locale": "sl-SI",
    "nextVisitAt": 1760988800018,
    "affinity": [
      "kids",
      "family"
    ]
  },
  {
    "id": "syn-9",
    "ua": "Mozilla/5.0 (Windows NT 10.0; Win64; x64) AppleWebKit/537.36 (KHTML, like Gecko) Chrome/141.0.7390.37 Safari/537.36",
    "locale": "de-DE",
    "nextVisitAt": 1760989153532,
    "affinity": [
      "sci-fi",
      "drama"
    ]
  },
  {
    "id": "syn-10",
    "ua": "Mozilla/5.0 (iPhone; CPU iPhone OS 15_0 like Mac OS X) AppleWebKit/605.1.15 (KHTML, like Gecko) Version/26.0 Mobile/15E148 Safari/604.1",
    "locale": "sl-SI",
    "nextVisitAt": 1761493431418,
    "affinity": [
      "kids",
      "family"
    ]
  },
  {
    "id": "syn-11",
    "ua": "Mozilla/5.0 (Windows NT 10.0; Win64; x64) AppleWebKit/537.36 (KHTML, like Gecko) Chrome/141.0.7390.37 Safari/537.36",
    "locale": "de-DE",
    "nextVisitAt": 1760921283977,
    "affinity": [
      "sci-fi",
      "drama"
    ]
  },
  {
    "id": "syn-12",
    "ua": "Mozilla/5.0 (Windows NT 10.0; Win64; x64) AppleWebKit/537.36 (KHTML, like Gecko) Chrome/141.0.7390.37 Safari/537.36",
    "locale": "sl-SI",
    "nextVisitAt": 1760916601816,
    "affinity": [
      "kids",
      "family"
    ]
  },
  {
    "id": "syn-13",
    "ua": "Mozilla/5.0 (iPhone; CPU iPhone OS 15_0 like Mac OS X) AppleWebKit/605.1.15 (KHTML, like Gecko) Version/26.0 Mobile/15E148 Safari/604.1",
    "locale": "de-DE",
    "nextVisitAt": 1760920460889,
    "affinity": [
      "sci-fi",
      "drama"
    ]
  },
  {
    "id": "syn-14",
    "ua": "Mozilla/5.0 (Windows NT 10.0; Win64; x64) AppleWebKit/537.36 (KHTML, like Gecko) Chrome/141.0.7390.37 Safari/537.36",
    "locale": "sl-SI",
    "nextVisitAt": 1760920211635,
    "affinity": [
      "kids",
      "family"
    ]
  },
  {
    "id": "syn-15",
    "ua": "Mozilla/5.0 (Windows NT 10.0; Win64; x64) AppleWebKit/537.36 (KHTML, like Gecko) Chrome/141.0.7390.37 Safari/537.36",
    "locale": "de-DE",
    "nextVisitAt": 1760920050607,
    "affinity": [
      "sci-fi",
      "drama"
    ]
  },
  {
    "id": "syn-16",
    "ua": "Mozilla/5.0 (iPhone; CPU iPhone OS 15_0 like Mac OS X) AppleWebKit/605.1.15 (KHTML, like Gecko) Version/26.0 Mobile/15E148 Safari/604.1",
    "locale": "sl-SI",
    "nextVisitAt": 1760921117834,
    "affinity": [
      "kids",
      "family"
    ]
  },
  {
    "id": "syn-17",
    "ua": "Mozilla/5.0 (Windows NT 10.0; Win64; x64) AppleWebKit/537.36 (KHTML, like Gecko) Chrome/141.0.7390.37 Safari/537.36",
    "locale": "de-DE",
    "nextVisitAt": 1760923032312,
    "affinity": [
      "sci-fi",
      "drama"
    ]
  },
  {
    "id": "syn-18",
    "ua": "Mozilla/5.0 (Windows NT 10.0; Win64; x64) AppleWebKit/537.36 (KHTML, like Gecko) Chrome/141.0.7390.37 Safari/537.36",
    "locale": "sl-SI",
    "nextVisitAt": 1760921039029,
    "affinity": [
      "kids",
      "family"
    ]
  },
  {
    "id": "syn-19",
    "ua": "Mozilla/5.0 (iPhone; CPU iPhone OS 15_0 like Mac OS X) AppleWebKit/605.1.15 (KHTML, like Gecko) Version/26.0 Mobile/15E148 Safari/604.1",
    "locale": "de-DE",
    "nextVisitAt": 1760920314436,
    "affinity": [
      "sci-fi",
      "drama"
    ]
  },
  {
    "id": "syn-20",
    "ua": "Mozilla/5.0 (Windows NT 10.0; Win64; x64) AppleWebKit/537.36 (KHTML, like Gecko) Chrome/141.0.7390.37 Safari/537.36",
    "locale": "sl-SI",
    "nextVisitAt": 1760923951573,
    "affinity": [
      "kids",
      "family"
    ]
  },
  {
    "id": "syn-21",
    "ua": "Mozilla/5.0 (Windows NT 10.0; Win64; x64) AppleWebKit/537.36 (KHTML, like Gecko) Chrome/141.0.7390.37 Safari/537.36",
    "locale": "de-DE",
    "nextVisitAt": 1760913585817,
    "affinity": [
      "sci-fi",
      "drama"
    ]
  },
  {
    "id": "syn-22",
    "ua": "Mozilla/5.0 (iPhone; CPU iPhone OS 15_0 like Mac OS X) AppleWebKit/605.1.15 (KHTML, like Gecko) Version/26.0 Mobile/15E148 Safari/604.1",
    "locale": "sl-SI",
    "nextVisitAt": 1760916081370,
    "affinity": [
      "kids",
      "family"
    ]
  },
  {
    "id": "syn-23",
    "ua": "Mozilla/5.0 (Windows NT 10.0; Win64; x64) AppleWebKit/537.36 (KHTML, like Gecko) Chrome/141.0.7390.37 Safari/537.36",
    "locale": "de-DE",
    "nextVisitAt": 1760921425996,
    "affinity": [
      "sci-fi",
      "drama"
    ]
  },
  {
    "id": "syn-24",
    "ua": "Mozilla/5.0 (Windows NT 10.0; Win64; x64) AppleWebKit/537.36 (KHTML, like Gecko) Chrome/141.0.7390.37 Safari/537.36",
    "locale": "sl-SI",
    "nextVisitAt": 1760916350083,
    "affinity": [
      "kids",
      "family"
    ]
  },
  {
    "id": "syn-25",
    "ua": "Mozilla/5.0 (iPhone; CPU iPhone OS 15_0 like Mac OS X) AppleWebKit/605.1.15 (KHTML, like Gecko) Version/26.0 Mobile/15E148 Safari/604.1",
    "locale": "de-DE",
    "nextVisitAt": 1760921589868,
    "affinity": [
      "sci-fi",
      "drama"
    ]
  },
  {
    "id": "syn-26",
    "ua": "Mozilla/5.0 (Windows NT 10.0; Win64; x64) AppleWebKit/537.36 (KHTML, like Gecko) Chrome/141.0.7390.37 Safari/537.36",
    "locale": "sl-SI",
    "nextVisitAt": 1760920475432,
    "affinity": [
      "kids",
      "family"
    ]
  },
  {
    "id": "syn-27",
    "ua": "Mozilla/5.0 (Windows NT 10.0; Win64; x64) AppleWebKit/537.36 (KHTML, like Gecko) Chrome/141.0.7390.37 Safari/537.36",
    "locale": "de-DE",
    "nextVisitAt": 1760924347049,
    "affinity": [
      "sci-fi",
      "drama"
    ]
  },
  {
    "id": "syn-28",
    "ua": "Mozilla/5.0 (iPhone; CPU iPhone OS 15_0 like Mac OS X) AppleWebKit/605.1.15 (KHTML, like Gecko) Version/26.0 Mobile/15E148 Safari/604.1",
    "locale": "sl-SI",
    "nextVisitAt": 1760922566612,
    "affinity": [
      "kids",
      "family"
    ]
  },
  {
    "id": "syn-29",
    "ua": "Mozilla/5.0 (Windows NT 10.0; Win64; x64) AppleWebKit/537.36 (KHTML, like Gecko) Chrome/141.0.7390.37 Safari/537.36",
    "locale": "de-DE",
    "nextVisitAt": 1760915153483,
    "affinity": [
      "sci-fi",
      "drama"
    ]
  },
  {
    "id": "syn-30",
    "ua": "Mozilla/5.0 (Windows NT 10.0; Win64; x64) AppleWebKit/537.36 (KHTML, like Gecko) Chrome/141.0.7390.37 Safari/537.36",
    "locale": "sl-SI",
    "nextVisitAt": 1760923567423,
    "affinity": [
      "kids",
      "family"
    ]
  },
  {
    "id": "syn-31",
    "ua": "Mozilla/5.0 (iPhone; CPU iPhone OS 15_0 like Mac OS X) AppleWebKit/605.1.15 (KHTML, like Gecko) Version/26.0 Mobile/15E148 Safari/604.1",
    "locale": "de-DE",
    "nextVisitAt": 1760921509016,
    "affinity": [
      "sci-fi",
      "drama"
    ]
  },
  {
    "id": "syn-32",
    "ua": "Mozilla/5.0 (Windows NT 10.0; Win64; x64) AppleWebKit/537.36 (KHTML, like Gecko) Chrome/141.0.7390.37 Safari/537.36",
    "locale": "sl-SI",
    "nextVisitAt": 1760914628780,
    "affinity": [
      "kids",
      "family"
    ]
  },
  {
    "id": "syn-33",
    "ua": "Mozilla/5.0 (Windows NT 10.0; Win64; x64) AppleWebKit/537.36 (KHTML, like Gecko) Chrome/141.0.7390.37 Safari/537.36",
    "locale": "de-DE",
    "nextVisitAt": 1760918701684,
    "affinity": [
      "sci-fi",
      "drama"
    ]
  },
  {
    "id": "syn-34",
    "ua": "Mozilla/5.0 (iPhone; CPU iPhone OS 15_0 like Mac OS X) AppleWebKit/605.1.15 (KHTML, like Gecko) Version/26.0 Mobile/15E148 Safari/604.1",
    "locale": "sl-SI",
    "nextVisitAt": 1760915262853,
    "affinity": [
      "kids",
      "family"
    ]
  },
  {
    "id": "syn-35",
    "ua": "Mozilla/5.0 (Windows NT 10.0; Win64; x64) AppleWebKit/537.36 (KHTML, like Gecko) Chrome/141.0.7390.37 Safari/537.36",
    "locale": "de-DE",
    "nextVisitAt": 1760917254808,
    "affinity": [
      "sci-fi",
      "drama"
    ]
  },
  {
    "id": "syn-36",
    "ua": "Mozilla/5.0 (Windows NT 10.0; Win64; x64) AppleWebKit/537.36 (KHTML, like Gecko) Chrome/141.0.7390.37 Safari/537.36",
    "locale": "sl-SI",
    "nextVisitAt": 1760920839445,
    "affinity": [
      "kids",
      "family"
    ]
  },
  {
    "id": "syn-37",
    "ua": "Mozilla/5.0 (iPhone; CPU iPhone OS 15_0 like Mac OS X) AppleWebKit/605.1.15 (KHTML, like Gecko) Version/26.0 Mobile/15E148 Safari/604.1",
    "locale": "de-DE",
    "nextVisitAt": 1760916598247,
    "affinity": [
      "sci-fi",
      "drama"
    ]
  },
  {
    "id": "syn-38",
    "ua": "Mozilla/5.0 (Windows NT 10.0; Win64; x64) AppleWebKit/537.36 (KHTML, like Gecko) Chrome/141.0.7390.37 Safari/537.36",
    "locale": "sl-SI",
    "nextVisitAt": 1760922154537,
    "affinity": [
      "kids",
      "family"
    ]
  },
  {
    "id": "syn-39",
    "ua": "Mozilla/5.0 (Windows NT 10.0; Win64; x64) AppleWebKit/537.36 (KHTML, like Gecko) Chrome/141.0.7390.37 Safari/537.36",
    "locale": "de-DE",
    "nextVisitAt": 1760921701868,
    "affinity": [
      "sci-fi",
      "drama"
    ]
  },
  {
    "id": "syn-40",
    "ua": "Mozilla/5.0 (iPhone; CPU iPhone OS 15_0 like Mac OS X) AppleWebKit/605.1.15 (KHTML, like Gecko) Version/26.0 Mobile/15E148 Safari/604.1",
    "locale": "sl-SI",
    "nextVisitAt": 1760915262173,
    "affinity": [
      "kids",
      "family"
    ]
  },
  {
    "id": "syn-41",
    "ua": "Mozilla/5.0 (Windows NT 10.0; Win64; x64) AppleWebKit/537.36 (KHTML, like Gecko) Chrome/141.0.7390.37 Safari/537.36",
    "locale": "de-DE",
    "nextVisitAt": 1760915530879,
    "affinity": [
      "sci-fi",
      "drama"
    ]
  },
  {
    "id": "syn-42",
    "ua": "Mozilla/5.0 (Windows NT 10.0; Win64; x64) AppleWebKit/537.36 (KHTML, like Gecko) Chrome/141.0.7390.37 Safari/537.36",
    "locale": "sl-SI",
    "nextVisitAt": 1760920733792,
    "affinity": [
      "kids",
      "family"
    ]
  },
  {
    "id": "syn-43",
    "ua": "Mozilla/5.0 (iPhone; CPU iPhone OS 15_0 like Mac OS X) AppleWebKit/605.1.15 (KHTML, like Gecko) Version/26.0 Mobile/15E148 Safari/604.1",
    "locale": "de-DE",
    "nextVisitAt": 1760920637498,
    "affinity": [
      "sci-fi",
      "drama"
    ]
  },
  {
    "id": "syn-44",
    "ua": "Mozilla/5.0 (Windows NT 10.0; Win64; x64) AppleWebKit/537.36 (KHTML, like Gecko) Chrome/141.0.7390.37 Safari/537.36",
    "locale": "sl-SI",
    "nextVisitAt": 1760921414787,
    "affinity": [
      "kids",
      "family"
    ]
  },
  {
    "id": "syn-45",
    "ua": "Mozilla/5.0 (Windows NT 10.0; Win64; x64) AppleWebKit/537.36 (KHTML, like Gecko) Chrome/141.0.7390.37 Safari/537.36",
    "locale": "de-DE",
    "nextVisitAt": 1760921677234,
    "affinity": [
      "sci-fi",
      "drama"
    ]
  },
  {
    "id": "syn-46",
    "ua": "Mozilla/5.0 (iPhone; CPU iPhone OS 15_0 like Mac OS X) AppleWebKit/605.1.15 (KHTML, like Gecko) Version/26.0 Mobile/15E148 Safari/604.1",
    "locale": "sl-SI",
    "nextVisitAt": 1760914901342,
    "affinity": [
      "kids",
      "family"
    ]
  },
  {
    "id": "syn-47",
    "ua": "Mozilla/5.0 (Windows NT 10.0; Win64; x64) AppleWebKit/537.36 (KHTML, like Gecko) Chrome/141.0.7390.37 Safari/537.36",
    "locale": "de-DE",
    "nextVisitAt": 1760916916649,
    "affinity": [
      "sci-fi",
      "drama"
    ]
  },
  {
    "id": "syn-48",
    "ua": "Mozilla/5.0 (Windows NT 10.0; Win64; x64) AppleWebKit/537.36 (KHTML, like Gecko) Chrome/141.0.7390.37 Safari/537.36",
    "locale": "sl-SI",
    "nextVisitAt": 1760922311275,
    "affinity": [
      "kids",
      "family"
    ]
  },
  {
    "id": "syn-49",
    "ua": "Mozilla/5.0 (iPhone; CPU iPhone OS 15_0 like Mac OS X) AppleWebKit/605.1.15 (KHTML, like Gecko) Version/26.0 Mobile/15E148 Safari/604.1",
    "locale": "de-DE",
    "nextVisitAt": 1760919390428,
    "affinity": [
      "sci-fi",
      "drama"
    ]
  },
  {
    "id": "syn-50",
    "ua": "Mozilla/5.0 (Windows NT 10.0; Win64; x64) AppleWebKit/537.36 (KHTML, like Gecko) Chrome/141.0.7390.37 Safari/537.36",
    "locale": "sl-SI",
    "nextVisitAt": 1760920805952,
    "affinity": [
      "kids",
      "family"
    ]
  },
  {
    "id": "syn-51",
    "ua": "Mozilla/5.0 (Windows NT 10.0; Win64; x64) AppleWebKit/537.36 (KHTML, like Gecko) Chrome/141.0.7390.37 Safari/537.36",
    "locale": "de-DE",
    "nextVisitAt": 1760915536579,
    "affinity": [
      "sci-fi",
      "drama"
    ]
  },
  {
    "id": "syn-52",
    "ua": "Mozilla/5.0 (iPhone; CPU iPhone OS 15_0 like Mac OS X) AppleWebKit/605.1.15 (KHTML, like Gecko) Version/26.0 Mobile/15E148 Safari/604.1",
    "locale": "sl-SI",
    "nextVisitAt": 1760917964792,
    "affinity": [
      "kids",
      "family"
    ]
  },
  {
    "id": "syn-53",
    "ua": "Mozilla/5.0 (Windows NT 10.0; Win64; x64) AppleWebKit/537.36 (KHTML, like Gecko) Chrome/141.0.7390.37 Safari/537.36",
    "locale": "de-DE",
    "nextVisitAt": 1760918616579,
    "affinity": [
      "sci-fi",
      "drama"
    ]
  },
  {
    "id": "syn-54",
    "ua": "Mozilla/5.0 (Windows NT 10.0; Win64; x64) AppleWebKit/537.36 (KHTML, like Gecko) Chrome/141.0.7390.37 Safari/537.36",
    "locale": "sl-SI",
    "nextVisitAt": 1760918608103,
    "affinity": [
      "kids",
      "family"
    ]
  },
  {
    "id": "syn-55",
    "ua": "Mozilla/5.0 (iPhone; CPU iPhone OS 15_0 like Mac OS X) AppleWebKit/605.1.15 (KHTML, like Gecko) Version/26.0 Mobile/15E148 Safari/604.1",
    "locale": "de-DE",
    "nextVisitAt": 1760916067219,
    "affinity": [
      "sci-fi",
      "drama"
    ]
  },
  {
    "id": "syn-56",
    "ua": "Mozilla/5.0 (Windows NT 10.0; Win64; x64) AppleWebKit/537.36 (KHTML, like Gecko) Chrome/141.0.7390.37 Safari/537.36",
    "locale": "sl-SI",
    "nextVisitAt": 1760915350149,
    "affinity": [
      "kids",
      "family"
    ]
  },
  {
    "id": "syn-57",
    "ua": "Mozilla/5.0 (Windows NT 10.0; Win64; x64) AppleWebKit/537.36 (KHTML, like Gecko) Chrome/141.0.7390.37 Safari/537.36",
    "locale": "de-DE",
    "nextVisitAt": 1760918904118,
    "affinity": [
      "sci-fi",
      "drama"
    ]
  },
  {
    "id": "syn-58",
    "ua": "Mozilla/5.0 (iPhone; CPU iPhone OS 15_0 like Mac OS X) AppleWebKit/605.1.15 (KHTML, like Gecko) Version/26.0 Mobile/15E148 Safari/604.1",
    "locale": "sl-SI",
    "nextVisitAt": 1760920855239,
    "affinity": [
      "kids",
      "family"
    ]
  },
  {
    "id": "syn-59",
    "ua": "Mozilla/5.0 (Windows NT 10.0; Win64; x64) AppleWebKit/537.36 (KHTML, like Gecko) Chrome/141.0.7390.37 Safari/537.36",
    "locale": "de-DE",
    "nextVisitAt": 1760914040168,
    "affinity": [
      "sci-fi",
      "drama"
    ]
  },
  {
    "id": "syn-60",
    "ua": "Mozilla/5.0 (Windows NT 10.0; Win64; x64) AppleWebKit/537.36 (KHTML, like Gecko) Chrome/141.0.7390.37 Safari/537.36",
    "locale": "sl-SI",
    "nextVisitAt": 1760920239514,
    "affinity": [
      "kids",
      "family"
    ]
  },
  {
    "id": "syn-61",
    "ua": "Mozilla/5.0 (iPhone; CPU iPhone OS 15_0 like Mac OS X) AppleWebKit/605.1.15 (KHTML, like Gecko) Version/26.0 Mobile/15E148 Safari/604.1",
    "locale": "de-DE",
    "nextVisitAt": 1760917860258,
    "affinity": [
      "sci-fi",
      "drama"
    ]
  },
  {
    "id": "syn-62",
    "ua": "Mozilla/5.0 (Windows NT 10.0; Win64; x64) AppleWebKit/537.36 (KHTML, like Gecko) Chrome/141.0.7390.37 Safari/537.36",
    "locale": "sl-SI",
    "nextVisitAt": 1760923442260,
    "affinity": [
      "kids",
      "family"
    ]
  },
  {
    "id": "syn-63",
    "ua": "Mozilla/5.0 (Windows NT 10.0; Win64; x64) AppleWebKit/537.36 (KHTML, like Gecko) Chrome/141.0.7390.37 Safari/537.36",
    "locale": "de-DE",
    "nextVisitAt": 1760922615568,
    "affinity": [
      "sci-fi",
      "drama"
    ]
  },
  {
    "id": "syn-64",
    "ua": "Mozilla/5.0 (iPhone; CPU iPhone OS 15_0 like Mac OS X) AppleWebKit/605.1.15 (KHTML, like Gecko) Version/26.0 Mobile/15E148 Safari/604.1",
    "locale": "sl-SI",
    "nextVisitAt": 1760919538712,
    "affinity": [
      "kids",
      "family"
    ]
  },
  {
    "id": "syn-65",
    "ua": "Mozilla/5.0 (Windows NT 10.0; Win64; x64) AppleWebKit/537.36 (KHTML, like Gecko) Chrome/141.0.7390.37 Safari/537.36",
    "locale": "de-DE",
    "nextVisitAt": 1760915113251,
    "affinity": [
      "sci-fi",
      "drama"
    ]
  },
  {
    "id": "syn-66",
    "ua": "Mozilla/5.0 (Windows NT 10.0; Win64; x64) AppleWebKit/537.36 (KHTML, like Gecko) Chrome/141.0.7390.37 Safari/537.36",
    "locale": "sl-SI",
    "nextVisitAt": 1760922282077,
    "affinity": [
      "kids",
      "family"
    ]
  },
  {
    "id": "syn-67",
    "ua": "Mozilla/5.0 (iPhone; CPU iPhone OS 15_0 like Mac OS X) AppleWebKit/605.1.15 (KHTML, like Gecko) Version/26.0 Mobile/15E148 Safari/604.1",
    "locale": "de-DE",
    "nextVisitAt": 1760921939255,
    "affinity": [
      "sci-fi",
      "drama"
    ]
  },
  {
    "id": "syn-68",
    "ua": "Mozilla/5.0 (Windows NT 10.0; Win64; x64) AppleWebKit/537.36 (KHTML, like Gecko) Chrome/141.0.7390.37 Safari/537.36",
    "locale": "sl-SI",
    "nextVisitAt": 1760917913595,
    "affinity": [
      "kids",
      "family"
    ]
  },
  {
    "id": "syn-69",
    "ua": "Mozilla/5.0 (Windows NT 10.0; Win64; x64) AppleWebKit/537.36 (KHTML, like Gecko) Chrome/141.0.7390.37 Safari/537.36",
    "locale": "de-DE",
    "nextVisitAt": 1760917110856,
    "affinity": [
      "sci-fi",
      "drama"
    ]
  },
  {
    "id": "syn-70",
    "ua": "Mozilla/5.0 (iPhone; CPU iPhone OS 15_0 like Mac OS X) AppleWebKit/605.1.15 (KHTML, like Gecko) Version/26.0 Mobile/15E148 Safari/604.1",
    "locale": "sl-SI",
    "nextVisitAt": 1760913925655,
    "affinity": [
      "kids",
      "family"
    ]
  },
  {
    "id": "syn-71",
    "ua": "Mozilla/5.0 (Windows NT 10.0; Win64; x64) AppleWebKit/537.36 (KHTML, like Gecko) Chrome/141.0.7390.37 Safari/537.36",
    "locale": "de-DE",
    "nextVisitAt": 1760923325812,
    "affinity": [
      "sci-fi",
      "drama"
    ]
  },
  {
    "id": "syn-72",
    "ua": "Mozilla/5.0 (Windows NT 10.0; Win64; x64) AppleWebKit/537.36 (KHTML, like Gecko) Chrome/141.0.7390.37 Safari/537.36",
    "locale": "sl-SI",
    "nextVisitAt": 1760918208642,
    "affinity": [
      "kids",
      "family"
    ]
  },
  {
    "id": "syn-73",
    "ua": "Mozilla/5.0 (iPhone; CPU iPhone OS 15_0 like Mac OS X) AppleWebKit/605.1.15 (KHTML, like Gecko) Version/26.0 Mobile/15E148 Safari/604.1",
    "locale": "de-DE",
    "nextVisitAt": 1760919972575,
    "affinity": [
      "sci-fi",
      "drama"
    ]
  },
  {
    "id": "syn-74",
    "ua": "Mozilla/5.0 (Windows NT 10.0; Win64; x64) AppleWebKit/537.36 (KHTML, like Gecko) Chrome/141.0.7390.37 Safari/537.36",
    "locale": "sl-SI",
    "nextVisitAt": 1760914765273,
    "affinity": [
      "kids",
      "family"
    ]
  },
  {
    "id": "syn-75",
    "ua": "Mozilla/5.0 (Windows NT 10.0; Win64; x64) AppleWebKit/537.36 (KHTML, like Gecko) Chrome/141.0.7390.37 Safari/537.36",
    "locale": "de-DE",
    "nextVisitAt": 1760916102903,
    "affinity": [
      "sci-fi",
      "drama"
    ]
  },
  {
    "id": "syn-76",
    "ua": "Mozilla/5.0 (iPhone; CPU iPhone OS 15_0 like Mac OS X) AppleWebKit/605.1.15 (KHTML, like Gecko) Version/26.0 Mobile/15E148 Safari/604.1",
    "locale": "sl-SI",
    "nextVisitAt": 1760923915412,
    "affinity": [
      "kids",
      "family"
    ]
  },
  {
    "id": "syn-77",
    "ua": "Mozilla/5.0 (Windows NT 10.0; Win64; x64) AppleWebKit/537.36 (KHTML, like Gecko) Chrome/141.0.7390.37 Safari/537.36",
    "locale": "de-DE",
    "nextVisitAt": 1760918465803,
    "affinity": [
      "sci-fi",
      "drama"
    ]
  },
  {
    "id": "syn-78",
    "ua": "Mozilla/5.0 (Windows NT 10.0; Win64; x64) AppleWebKit/537.36 (KHTML, like Gecko) Chrome/141.0.7390.37 Safari/537.36",
    "locale": "sl-SI",
    "nextVisitAt": 1760913868733,
    "affinity": [
      "kids",
      "family"
    ]
  },
  {
    "id": "syn-79",
    "ua": "Mozilla/5.0 (iPhone; CPU iPhone OS 15_0 like Mac OS X) AppleWebKit/605.1.15 (KHTML, like Gecko) Version/26.0 Mobile/15E148 Safari/604.1",
    "locale": "de-DE",
    "nextVisitAt": 1760917477419,
    "affinity": [
      "sci-fi",
      "drama"
    ]
  },
  {
    "id": "syn-80",
    "ua": "Mozilla/5.0 (Windows NT 10.0; Win64; x64) AppleWebKit/537.36 (KHTML, like Gecko) Chrome/141.0.7390.37 Safari/537.36",
    "locale": "sl-SI",
    "nextVisitAt": 1760916861937,
    "affinity": [
      "kids",
      "family"
    ]
  },
  {
    "id": "syn-81",
    "ua": "Mozilla/5.0 (Windows NT 10.0; Win64; x64) AppleWebKit/537.36 (KHTML, like Gecko) Chrome/141.0.7390.37 Safari/537.36",
    "locale": "de-DE",
    "nextVisitAt": 1760920627557,
    "affinity": [
      "sci-fi",
      "drama"
    ]
  },
  {
    "id": "syn-82",
    "ua": "Mozilla/5.0 (iPhone; CPU iPhone OS 15_0 like Mac OS X) AppleWebKit/605.1.15 (KHTML, like Gecko) Version/26.0 Mobile/15E148 Safari/604.1",
    "locale": "sl-SI",
    "nextVisitAt": 1760923354592,
    "affinity": [
      "kids",
      "family"
    ]
  },
  {
    "id": "syn-83",
    "ua": "Mozilla/5.0 (Windows NT 10.0; Win64; x64) AppleWebKit/537.36 (KHTML, like Gecko) Chrome/141.0.7390.37 Safari/537.36",
    "locale": "de-DE",
    "nextVisitAt": 1760923703623,
    "affinity": [
      "sci-fi",
      "drama"
    ]
  },
  {
    "id": "syn-84",
    "ua": "Mozilla/5.0 (Windows NT 10.0; Win64; x64) AppleWebKit/537.36 (KHTML, like Gecko) Chrome/141.0.7390.37 Safari/537.36",
    "locale": "sl-SI",
    "nextVisitAt": 1760922063844,
    "affinity": [
      "kids",
      "family"
    ]
  },
  {
    "id": "syn-85",
    "ua": "Mozilla/5.0 (iPhone; CPU iPhone OS 15_0 like Mac OS X) AppleWebKit/605.1.15 (KHTML, like Gecko) Version/26.0 Mobile/15E148 Safari/604.1",
    "locale": "de-DE",
    "nextVisitAt": 1760923974992,
    "affinity": [
      "sci-fi",
      "drama"
    ]
  },
  {
    "id": "syn-86",
    "ua": "Mozilla/5.0 (Windows NT 10.0; Win64; x64) AppleWebKit/537.36 (KHTML, like Gecko) Chrome/141.0.7390.37 Safari/537.36",
    "locale": "sl-SI",
    "nextVisitAt": 1760923444173,
    "affinity": [
      "kids",
      "family"
    ]
  },
  {
    "id": "syn-87",
    "ua": "Mozilla/5.0 (Windows NT 10.0; Win64; x64) AppleWebKit/537.36 (KHTML, like Gecko) Chrome/141.0.7390.37 Safari/537.36",
    "locale": "de-DE",
    "nextVisitAt": 1760918241630,
    "affinity": [
      "sci-fi",
      "drama"
    ]
  },
  {
    "id": "syn-88",
    "ua": "Mozilla/5.0 (iPhone; CPU iPhone OS 15_0 like Mac OS X) AppleWebKit/605.1.15 (KHTML, like Gecko) Version/26.0 Mobile/15E148 Safari/604.1",
    "locale": "sl-SI",
    "nextVisitAt": 1760917612991,
    "affinity": [
      "kids",
      "family"
    ]
  },
  {
    "id": "syn-89",
    "ua": "Mozilla/5.0 (Windows NT 10.0; Win64; x64) AppleWebKit/537.36 (KHTML, like Gecko) Chrome/141.0.7390.37 Safari/537.36",
    "locale": "de-DE",
    "nextVisitAt": 1760913896676,
    "affinity": [
      "sci-fi",
      "drama"
    ]
  },
  {
    "id": "syn-90",
    "ua": "Mozilla/5.0 (Windows NT 10.0; Win64; x64) AppleWebKit/537.36 (KHTML, like Gecko) Chrome/141.0.7390.37 Safari/537.36",
    "locale": "sl-SI",
    "nextVisitAt": 1760914783373,
    "affinity": [
      "kids",
      "family"
    ]
  },
  {
    "id": "syn-91",
    "ua": "Mozilla/5.0 (iPhone; CPU iPhone OS 15_0 like Mac OS X) AppleWebKit/605.1.15 (KHTML, like Gecko) Version/26.0 Mobile/15E148 Safari/604.1",
    "locale": "de-DE",
    "nextVisitAt": 1760915205312,
    "affinity": [
      "sci-fi",
      "drama"
    ]
  },
  {
    "id": "syn-92",
    "ua": "Mozilla/5.0 (Windows NT 10.0; Win64; x64) AppleWebKit/537.36 (KHTML, like Gecko) Chrome/141.0.7390.37 Safari/537.36",
    "locale": "sl-SI",
    "nextVisitAt": 1760914825134,
    "affinity": [
      "kids",
      "family"
    ]
  },
  {
    "id": "syn-93",
    "ua": "Mozilla/5.0 (Windows NT 10.0; Win64; x64) AppleWebKit/537.36 (KHTML, like Gecko) Chrome/141.0.7390.37 Safari/537.36",
    "locale": "de-DE",
    "nextVisitAt": 1760922313448,
    "affinity": [
      "sci-fi",
      "drama"
    ]
  },
  {
    "id": "syn-94",
    "ua": "Mozilla/5.0 (iPhone; CPU iPhone OS 15_0 like Mac OS X) AppleWebKit/605.1.15 (KHTML, like Gecko) Version/26.0 Mobile/15E148 Safari/604.1",
    "locale": "sl-SI",
    "nextVisitAt": 1760922047463,
    "affinity": [
      "kids",
      "family"
    ]
  },
  {
    "id": "syn-95",
    "ua": "Mozilla/5.0 (Windows NT 10.0; Win64; x64) AppleWebKit/537.36 (KHTML, like Gecko) Chrome/141.0.7390.37 Safari/537.36",
    "locale": "de-DE",
    "nextVisitAt": 1760923303804,
    "affinity": [
      "sci-fi",
      "drama"
    ]
  },
  {
    "id": "syn-96",
    "ua": "Mozilla/5.0 (Windows NT 10.0; Win64; x64) AppleWebKit/537.36 (KHTML, like Gecko) Chrome/141.0.7390.37 Safari/537.36",
    "locale": "sl-SI",
    "nextVisitAt": 1760920468776,
    "affinity": [
      "kids",
      "family"
    ]
  },
  {
    "id": "syn-97",
    "ua": "Mozilla/5.0 (iPhone; CPU iPhone OS 15_0 like Mac OS X) AppleWebKit/605.1.15 (KHTML, like Gecko) Version/26.0 Mobile/15E148 Safari/604.1",
    "locale": "de-DE",
    "nextVisitAt": 1760921187602,
    "affinity": [
      "sci-fi",
      "drama"
    ]
  },
  {
    "id": "syn-98",
    "ua": "Mozilla/5.0 (Windows NT 10.0; Win64; x64) AppleWebKit/537.36 (KHTML, like Gecko) Chrome/141.0.7390.37 Safari/537.36",
    "locale": "sl-SI",
    "nextVisitAt": 1760920493188,
    "affinity": [
      "kids",
      "family"
    ]
  },
  {
    "id": "syn-99",
    "ua": "Mozilla/5.0 (Windows NT 10.0; Win64; x64) AppleWebKit/537.36 (KHTML, like Gecko) Chrome/141.0.7390.37 Safari/537.36",
    "locale": "de-DE",
    "nextVisitAt": 1760913900594,
    "affinity": [
      "sci-fi",
      "drama"
    ]
  },
  {
    "id": "syn-100",
    "ua": "Mozilla/5.0 (iPhone; CPU iPhone OS 15_0 like Mac OS X) AppleWebKit/605.1.15 (KHTML, like Gecko) Version/26.0 Mobile/15E148 Safari/604.1",
    "locale": "sl-SI",
    "nextVisitAt": 1760918771366,
    "affinity": [
      "kids",
      "family"
    ]
  },
  {
    "id": "syn-101",
    "ua": "Mozilla/5.0 (Windows NT 10.0; Win64; x64) AppleWebKit/537.36 (KHTML, like Gecko) Chrome/141.0.7390.37 Safari/537.36",
    "locale": "de-DE",
    "nextVisitAt": 1760918731448,
    "affinity": [
      "sci-fi",
      "drama"
    ]
  },
  {
    "id": "syn-102",
    "ua": "Mozilla/5.0 (Windows NT 10.0; Win64; x64) AppleWebKit/537.36 (KHTML, like Gecko) Chrome/141.0.7390.37 Safari/537.36",
    "locale": "sl-SI",
    "nextVisitAt": 1760915112149,
    "affinity": [
      "kids",
      "family"
    ]
  },
  {
    "id": "syn-103",
    "ua": "Mozilla/5.0 (iPhone; CPU iPhone OS 15_0 like Mac OS X) AppleWebKit/605.1.15 (KHTML, like Gecko) Version/26.0 Mobile/15E148 Safari/604.1",
    "locale": "de-DE",
    "nextVisitAt": 1760919130075,
    "affinity": [
      "sci-fi",
      "drama"
    ]
  },
  {
    "id": "syn-104",
    "ua": "Mozilla/5.0 (Windows NT 10.0; Win64; x64) AppleWebKit/537.36 (KHTML, like Gecko) Chrome/141.0.7390.37 Safari/537.36",
    "locale": "sl-SI",
    "nextVisitAt": 1760916024916,
    "affinity": [
      "kids",
      "family"
    ]
  },
  {
    "id": "syn-105",
    "ua": "Mozilla/5.0 (Windows NT 10.0; Win64; x64) AppleWebKit/537.36 (KHTML, like Gecko) Chrome/141.0.7390.37 Safari/537.36",
    "locale": "de-DE",
    "nextVisitAt": 1760924147092,
    "affinity": [
      "sci-fi",
      "drama"
    ]
  },
  {
    "id": "syn-106",
    "ua": "Mozilla/5.0 (iPhone; CPU iPhone OS 15_0 like Mac OS X) AppleWebKit/605.1.15 (KHTML, like Gecko) Version/26.0 Mobile/15E148 Safari/604.1",
    "locale": "sl-SI",
    "nextVisitAt": 1760916598732,
    "affinity": [
      "kids",
      "family"
    ]
  },
  {
    "id": "syn-107",
    "ua": "Mozilla/5.0 (Windows NT 10.0; Win64; x64) AppleWebKit/537.36 (KHTML, like Gecko) Chrome/141.0.7390.37 Safari/537.36",
    "locale": "de-DE",
    "nextVisitAt": 1760923972573,
    "affinity": [
      "sci-fi",
      "drama"
    ]
  },
  {
    "id": "syn-108",
    "ua": "Mozilla/5.0 (Windows NT 10.0; Win64; x64) AppleWebKit/537.36 (KHTML, like Gecko) Chrome/141.0.7390.37 Safari/537.36",
    "locale": "sl-SI",
    "nextVisitAt": 1760919142059,
    "affinity": [
      "kids",
      "family"
    ]
  },
  {
    "id": "syn-109",
    "ua": "Mozilla/5.0 (iPhone; CPU iPhone OS 15_0 like Mac OS X) AppleWebKit/605.1.15 (KHTML, like Gecko) Version/26.0 Mobile/15E148 Safari/604.1",
    "locale": "de-DE",
    "nextVisitAt": 1760919791901,
    "affinity": [
      "sci-fi",
      "drama"
    ]
  },
  {
    "id": "syn-110",
    "ua": "Mozilla/5.0 (Windows NT 10.0; Win64; x64) AppleWebKit/537.36 (KHTML, like Gecko) Chrome/141.0.7390.37 Safari/537.36",
    "locale": "sl-SI",
    "nextVisitAt": 1760919095513,
    "affinity": [
      "kids",
      "family"
    ]
  },
  {
    "id": "syn-111",
    "ua": "Mozilla/5.0 (Windows NT 10.0; Win64; x64) AppleWebKit/537.36 (KHTML, like Gecko) Chrome/141.0.7390.37 Safari/537.36",
    "locale": "de-DE",
    "nextVisitAt": 1760916259064,
    "affinity": [
      "sci-fi",
      "drama"
    ]
  },
  {
    "id": "syn-112",
    "ua": "Mozilla/5.0 (iPhone; CPU iPhone OS 15_0 like Mac OS X) AppleWebKit/605.1.15 (KHTML, like Gecko) Version/26.0 Mobile/15E148 Safari/604.1",
    "locale": "sl-SI",
    "nextVisitAt": 1760913827415,
    "affinity": [
      "kids",
      "family"
    ]
  },
  {
    "id": "syn-113",
    "ua": "Mozilla/5.0 (Windows NT 10.0; Win64; x64) AppleWebKit/537.36 (KHTML, like Gecko) Chrome/141.0.7390.37 Safari/537.36",
    "locale": "de-DE",
    "nextVisitAt": 1760917698238,
    "affinity": [
      "sci-fi",
      "drama"
    ]
  },
  {
    "id": "syn-114",
    "ua": "Mozilla/5.0 (Windows NT 10.0; Win64; x64) AppleWebKit/537.36 (KHTML, like Gecko) Chrome/141.0.7390.37 Safari/537.36",
    "locale": "sl-SI",
    "nextVisitAt": 1760923738891,
    "affinity": [
      "kids",
      "family"
    ]
  },
  {
    "id": "syn-115",
    "ua": "Mozilla/5.0 (iPhone; CPU iPhone OS 15_0 like Mac OS X) AppleWebKit/605.1.15 (KHTML, like Gecko) Version/26.0 Mobile/15E148 Safari/604.1",
    "locale": "de-DE",
    "nextVisitAt": 1760921126132,
    "affinity": [
      "sci-fi",
      "drama"
    ]
  },
  {
    "id": "syn-116",
    "ua": "Mozilla/5.0 (Windows NT 10.0; Win64; x64) AppleWebKit/537.36 (KHTML, like Gecko) Chrome/141.0.7390.37 Safari/537.36",
    "locale": "sl-SI",
    "nextVisitAt": 1760924205941,
    "affinity": [
      "kids",
      "family"
    ]
  },
  {
    "id": "syn-117",
    "ua": "Mozilla/5.0 (Windows NT 10.0; Win64; x64) AppleWebKit/537.36 (KHTML, like Gecko) Chrome/141.0.7390.37 Safari/537.36",
    "locale": "de-DE",
    "nextVisitAt": 1760915948787,
    "affinity": [
      "sci-fi",
      "drama"
    ]
  },
  {
    "id": "syn-118",
    "ua": "Mozilla/5.0 (iPhone; CPU iPhone OS 15_0 like Mac OS X) AppleWebKit/605.1.15 (KHTML, like Gecko) Version/26.0 Mobile/15E148 Safari/604.1",
    "locale": "sl-SI",
    "nextVisitAt": 1760916959652,
    "affinity": [
      "kids",
      "family"
    ]
  },
  {
    "id": "syn-119",
    "ua": "Mozilla/5.0 (Windows NT 10.0; Win64; x64) AppleWebKit/537.36 (KHTML, like Gecko) Chrome/141.0.7390.37 Safari/537.36",
    "locale": "de-DE",
    "nextVisitAt": 1760922791105,
    "affinity": [
      "sci-fi",
      "drama"
    ]
  },
  {
    "id": "syn-120",
    "ua": "Mozilla/5.0 (Windows NT 10.0; Win64; x64) AppleWebKit/537.36 (KHTML, like Gecko) Chrome/141.0.7390.37 Safari/537.36",
    "locale": "sl-SI",
    "nextVisitAt": 1760923775924,
    "affinity": [
      "kids",
      "family"
    ]
  }
]